{"locations":[
{"CountryId" : "2840", "Country": "USA", "RegionId" : "21176", "Region" : "Texas", "MetroId":"1026759", "Metro": "San Antonio-TX", "CityId": "2454545", "City": "San Antonio", "PostalCodeId": "9028086", "PostalCode": "78246"},
{"CountryId" : "2840", "Country": "USA", "RegionId" : "21176", "Region" : "Texas", "MetroId":"1026759", "Metro": "San Antonio-TX", "CityId": "2454545", "City": "San Antonio", "PostalCodeId": "9028086", "PostalCode": "78246"},
{"CountryId" : "2840", "Country": "USA", "RegionId" : "21176", "Region" : "Texas", "MetroId":"1026759", "Metro": "San Antonio-TX", "CityId": "2454545", "City": "San Antonio", "PostalCodeId": "9028086", "PostalCode": "78244"},
{"CountryId" : "2840", "Country": "USA", "RegionId" : "21176", "Region" : "Texas", "MetroId":"1026759", "Metro": "San Antonio-TX", "CityId": "2454545", "City": "San Antonio", "PostalCodeId": "9028086", "PostalCode": "78242"},
{"CountryId" : "2840", "Country": "USA", "RegionId" : "21176", "Region" : "Texas", "MetroId":"1026759", "Metro": "San Antonio-TX", "CityId": "2454545", "City": "San Antonio", "PostalCodeId": "9028086", "PostalCode": "78241"},
{"CountryId" : "2840", "Country": "USA", "RegionId" : "21176", "Region" : "Texas", "MetroId":"1026759", "Metro": "Dallas Fort Wt-TX", "CityId": "2454545", "City": "Dallas", "PostalCodeId": "9028096", "PostalCode": "78250"},
{"CountryId" : "2840", "Country": "USA", "RegionId" : "21176", "Region" : "Texas", "MetroId":"1026759", "Metro": "Dallas Fort Wt-TX", "CityId": "2454545", "City": "Dallas", "PostalCodeId": "9028096", "PostalCode": "78251"},
{"CountryId" : "2840", "Country": "USA", "RegionId" : "21176", "Region" : "Texas", "MetroId":"1026759", "Metro": "Dallas Fort Wt-TX", "CityId": "2454545", "City": "Dallas", "PostalCodeId": "9028096", "PostalCode": "78252"},
{"CountryId" : "2840", "Country": "USA", "RegionId" : "21176", "Region" : "Texas", "MetroId":"1026759", "Metro": "Dallas Fort Wt-TX", "CityId": "2454545", "City": "Dallas", "PostalCodeId": "9028096", "PostalCode": "78253"},
{"CountryId" : "2840", "Country": "USA", "RegionId" : "21176", "Region" : "Texas", "MetroId":"1026759", "Metro": "Dallas Fort Wt-TX", "CityId": "2454545", "City": "Dallas", "PostalCodeId": "9028096", "PostalCode": "78254"},
{"CountryId" : "2840", "Country": "USA", "RegionId" : "21176", "Region" : "Texas", "MetroId":"1026759", "Metro": "Dallas Fort Wt-TX", "CityId": "2454545", "City": "Dallas", "PostalCodeId": "9028096", "PostalCode": "78255"}
]
}